ubleiden_theme/__init__.py
ubleiden_theme/basechild.html
ubleiden_theme/home.html
ubleiden_theme/main.html
ubleiden_theme/mkdocs_theme.yml
ubleiden_theme/assets/images/favicon.png
ubleiden_theme/assets/images/logo.png
ubleiden_theme/assets/stylesheets/extra.css
mkdocs_ubleiden_theme-1.2.0.dist-info/METADATA
mkdocs_ubleiden_theme-1.2.0.dist-info/WHEEL
mkdocs_ubleiden_theme-1.2.0.dist-info/entry_points.txt
mkdocs_ubleiden_theme-1.2.0.dist-info/licenses/LICENSE
mkdocs_ubleiden_theme-1.2.0.dist-info/RECORD
