Metadata-Version: 2.4
Name: mkdocs-ubleiden-theme
Version: 1.2.0
Summary: UBL theme for MkDocs, extending Material for MkDocs
Project-URL: Homepage, https://github.com/LeidenUniversityLibrary/mkdocs-ubleiden-theme
Project-URL: Issues, https://github.com/LeidenUniversityLibrary/mkdocs-ubleiden-theme/issues
Author-email: Ben Companjen <ben@companjen.name>
License-Expression: GPL-3.0
License-File: LICENSE
Keywords: mkdocs,theme
Classifier: Development Status :: 4 - Beta
Classifier: Intended Audience :: Developers
Classifier: Operating System :: OS Independent
Classifier: Programming Language :: Python :: 3
Classifier: Topic :: Documentation
Classifier: Topic :: Software Development :: Documentation
Requires-Python: >=3.8
Requires-Dist: mkdocs-material>=8.5.11
